{
  "$schema": "https://developer.microsoft.com/json-schemas/fabric/item/report/definition/visualContainer/2.8.0/schema.json",
  "name": "b18dea367b25f249b040",
  "position": {
    "x": 824.13407821229055,
    "y": 180.55865921787711,
    "z": 2000,
    "height": 355.75418994413411,
    "width": 455.86592178770951,
    "tabOrder": 2000
  },
  "visual": {
    "visualType": "advancedSlicerVisual",
    "query": {
      "queryState": {
        "Label": {
          "projections": [
            {
              "field": {
                "Aggregation": {
                  "Expression": {
                    "Column": {
                      "Expression": {
                        "SourceRef": {
                          "Entity": "Product"
                        }
                      },
                      "Property": "Color"
                    }
                  },
                  "Function": 3
                }
              },
              "queryRef": "Min(Product.Color)",
              "nativeQueryRef": "First Color"
            }
          ]
        },
        "Values": {
          "projections": [
            {
              "field": {
                "Column": {
                  "Expression": {
                    "SourceRef": {
                      "Entity": "Product"
                    }
                  },
                  "Property": "Color"
                }
              },
              "queryRef": "Product.Color",
              "nativeQueryRef": "Color"
            }
          ]
        }
      },
      "sortDefinition": {
        "sort": [
          {
            "field": {
              "Column": {
                "Expression": {
                  "SourceRef": {
                    "Entity": "Product"
                  }
                },
                "Property": "Color"
              }
            },
            "direction": "Ascending"
          }
        ]
      }
    },
    "objects": {
      "layout": [
        {
          "properties": {
            "autoGrid": {
              "expr": {
                "Literal": {
                  "Value": "true"
                }
              }
            },
            "columnCount": {
              "expr": {
                "Literal": {
                  "Value": "3L"
                }
              }
            },
            "rowCount": {
              "expr": {
                "Literal": {
                  "Value": "3L"
                }
              }
            }
          }
        }
      ],
      "label": [
        {
          "properties": {
            "show": {
              "expr": {
                "Literal": {
                  "Value": "false"
                }
              }
            }
          },
          "selector": {
            "id": "default"
          }
        }
      ]
    },
    "drillFilterOtherVisuals": true
  }
}